railyard/__init__.py
railyard/app.py
railyard/entrypoint.py
railyard/tests/__init__.py
railyard/tests/test_app.py
railyard/tests/test_app1.yaml
railyard/tests/test_app2.yaml
railyard/tests/test_app3.yaml
railyard/tests/test_dispatch1.yaml
railyard/tests/test_dispatch2.yaml
railyard/tests/test_dispatch3.yaml
railyard/tests/test_entrypoint.py
railyard/tests/test_static_file
railyard-0.1.0.dist-info/COPYING
railyard-0.1.0.dist-info/METADATA
railyard-0.1.0.dist-info/WHEEL
railyard-0.1.0.dist-info/entry_points.txt
railyard-0.1.0.dist-info/top_level.txt
railyard-0.1.0.dist-info/RECORD
