Metadata-Version: 2.1
Name: railyard
Version: 0.1.0
Summary: Simple local application development server
Home-page: https://bitbucket.org/nielsenb/railyard
Author: Brandon Nielsen
Author-email: nielsenb@jetfuse.net
License: UNKNOWN
Project-URL: Documentation, https://railyard.readthedocs.io/en/latest/
Project-URL: Source, https://bitbucket.org/nielsenb/railyard
Project-URL: Tracker, https://bitbucket.org/nielsenb/railyard/issues
Keywords: webapp dispatch routing
Platform: UNKNOWN
Classifier: Development Status :: 3 - Alpha
Classifier: Intended Audience :: Developers
Classifier: License :: OSI Approved :: GNU General Public License v3 or later (GPLv3+)
Classifier: Operating System :: OS Independent
Classifier: Programming Language :: Python
Classifier: Programming Language :: Python :: 3
Classifier: Programming Language :: Python :: 3.7
Classifier: Topic :: Software Development :: Libraries :: Python Modules
Requires-Python: >=3.7
Requires-Dist: gunicorn
Requires-Dist: pyyaml
